[{"title":"Connected","artist":"Dust, Peace-Ka"},{"title":"Mathematical Error","artist":"Dust"},{"title":"Crazy","artist":"Dust, Peace-Ka"},{"title":"Blue Eyed Wildcat","artist":"Dust"},{"title":"That's the Way It Is","artist":"Dust, LsDirty"},{"title":"Vulgar Display of Power","artist":"Dust"},{"title":"Avocado Salmon Madness","artist":"Dust"},{"title":"Dark Energy","artist":"Dust, Delirium Tremens"},{"title":"Slaves","artist":"Dust, Liftshift"},{"title":"Thirteen","artist":"Dust"},{"title":"Crisis","artist":"Dust"},{"title":"Shiva - Original Mix","artist":"Zyce, Morten Granau"},{"title":"We Come In Peace - Talpa Remix","artist":"Liquid Soul, Zyce, Solar Kid"},{"title":"Violenty Happy - Original Mix","artist":"Talpa"},{"title":"First Dose of Dmt","artist":"Ectima"},{"title":"La La La - Original Mix","artist":"Talpa"},{"title":"Disturbia","artist":"Vertex, Invisible Reality, Lydia Delay"},{"title":"Sensory System","artist":"Flegma"},{"title":"Here Come The Sun","artist":"Zyce, Talpa"},{"title":"Perfect Psychopath - Original Mix","artist":"Talpa"},{"title":"Being Human","artist":"Genetrick"},{"title":"Hemija","artist":"Molok, Vertex, Subliminal Codes"},{"title":"The Moon - Flegma Remix","artist":"Talpa, Flegma"},{"title":"Boketto","artist":"Flegma"},{"title":"The Ritual - Flegma Remix","artist":"Zyce, Flegma"},{"title":"Human Planet - Original Mix","artist":"Flegma"},{"title":"Dark Side - Talpa Remix","artist":"Zyce, Aquafeel, Talpa"},{"title":"Lapses Of Sanity","artist":"Talpa"},{"title":"Mrs. Rottencandy","artist":"Talpa"},{"title":"Ancient Tribes","artist":"Sonic Entity"},{"title":"Capacity - Original Mix","artist":"Flegma"},{"title":"Average Looking Bicycle","artist":"Talpa"},{"title":"Soul Protector","artist":"Flegma"},{"title":"Point of No Return","artist":"Talpa"},{"title":"Violently Happy - Zyce Halloween Remix","artist":"Talpa"},{"title":"What Can You Do","artist":"Sonic Entity, Zyce"},{"title":"Born This Way","artist":"Talpa, Purple Hayes"},{"title":"Tidal","artist":"Zyce, Sonic Entity"},{"title":"Dreamcatcher - Original Mix","artist":"Sonic Entity"},{"title":"Sons of The Future","artist":"Zyce, Arhetip"},{"title":"Transience - Original Mix","artist":"Arhetip"},{"title":"World Rebirth Party - Arhetip Remix","artist":"Zyce"},{"title":"Time Machine","artist":"Waveform"},{"title":"Extraterrestrial Beings","artist":"Waveform"},{"title":"Moment To Moment","artist":"Waveform, Aquafeel"},{"title":"Intelligent Machines - Suduaya Remix","artist":"Waveform, Suduaya"},{"title":"Awakening of The Slavic Spirit - Original Mix","artist":"Zyce"},{"title":"Auditory Hallucinations - Original Mix","artist":"Aquafeel, Headweller"},{"title":"Eagle Horison - Original Mix","artist":"Zyce"},{"title":"Galactic Frequency","artist":"Vertex, INTERPULSE"},{"title":"Heart Beat - Original Mix","artist":"Vertex"},{"title":"Star Dust","artist":"Zyce"},{"title":"Witchcraft","artist":"Zyce, Sub6"},{"title":"Ayahuasca - Original Mix","artist":"Zyce"},{"title":"Human Planet - Original Mix","artist":"Flegma"},{"title":"Mathematical Existance - Original Mix","artist":"Talpa"},{"title":"Booby Trap - Original Mix","artist":"Talpa"},{"title":"World Rebirth Party - Original Mix","artist":"Zyce"},{"title":"Curiosity Killed The Cat - Original Mix","artist":"Talpa"},{"title":"Magic Shrooms - Original Mix","artist":"Zyce"},{"title":"Dark Days - Original Mix","artist":"Talpa"},{"title":"Letter From Vienna - Original Mix","artist":"Talpa"},{"title":"Going Home - Original Mix","artist":"Talpa"},{"title":"Emo Robot - Original Mix","artist":"Talpa"},{"title":"Hypnotic Daze","artist":"Arhetip"},{"title":"Shades Of Confusion","artist":"Aquafeel"},{"title":"The Ravenant - Original Mix","artist":"Aquafeel"},{"title":"Mongol - Original Mix","artist":"Genetrick"},{"title":"Japan","artist":"Kalki"},{"title":"The Sage","artist":"Starlab (IN)"},{"title":"Invisible Spectrum","artist":"Makida"},{"title":"Witchcraft - Makida Remix","artist":"Zyce, Sub6, Makida"},{"title":"The Protocol - Original Mix","artist":"Zyce, Liquid Soul, Solar Kid"},{"title":"Witchcraft - Original Mix","artist":"Zyce, Sub6"},{"title":"Son Of Night - Original Mix","artist":"Zyce, Gaudium"},{"title":"The Ritual - Original Mix","artist":"Zyce"},{"title":"Leviathan","artist":"MODERN8, Creative-X"},{"title":"Human Race","artist":"Ectima"},{"title":"Who Attacks Me","artist":"Ectima"},{"title":"Symbiosis","artist":"Ectima"},{"title":"Balkan Clash","artist":"Ectima"},{"title":"Perpetual","artist":"Ectima, Aquafeel"},{"title":"Immortalize","artist":"Ectima"},{"title":"Ground Tracer - Orginal Mix","artist":"Ectima"},{"title":"Sedition","artist":"Ectima"},{"title":"Taken","artist":"Ectima"},{"title":"Everything Is Possible","artist":"Lyctum, Ectima"},{"title":"Crystal Zombie","artist":"Ectima, Phaxe"},{"title":"Gather - Ectima Remix","artist":"Artifact, Ectima"},{"title":"Ground Control - Ectima Remix","artist":"Zen Mechanics, Ectima"},{"title":"Discombobulate","artist":"Ectima"},{"title":"The Claymore","artist":"Ectima, Talpa"},{"title":"Symbiosis - Original Mix","artist":"Ectima"},{"title":"Immortalize - Original Mix","artist":"Ectima"},{"title":"Crystal Zombie - Original Mix","artist":"Ectima, Phaxe"},{"title":"Ground Control - Ectima Remix","artist":"Zen Mechanics"},{"title":"Gather - Ectima Remix","artist":"Artifact"},{"title":"Balkan Clash - Original Mix","artist":"Ectima"},{"title":"Human Race - Original Mix","artist":"Ectima"},{"title":"Find The Way Out","artist":"Ectima"},{"title":"Logatone","artist":"Ectima"},{"title":"Evil Spirits","artist":"Ectima"},{"title":"Labyrinth","artist":"Ectima"},{"title":"Black Humor","artist":"Ectima"},{"title":"Ectima & PhaseTech - Spliced","artist":"Ectima"},{"title":"Metal Isolation - Remix","artist":"Ectima"},{"title":"Home Treatment","artist":"Ectima"},{"title":"Morning Star","artist":"Shogan"},{"title":"Absence","artist":"Talpa"},{"title":"Zen","artist":"Sonic Entity"},{"title":"Qoom","artist":"E-Clip"},{"title":"Insanity","artist":"Ectima"},{"title":"Istok I Zapad","artist":"Vertex, Ascent"},{"title":"Puls","artist":"Freaked Frequency"},{"title":"Slava","artist":"Zyce"},{"title":"Walbahaar","artist":"Shogan, Norma Project"},{"title":"Tama","artist":"Flegma"},{"title":"Soulshine","artist":"Lyktum"},{"title":"Ghost In The Shell","artist":"Relativ"},{"title":"Clear Head","artist":"Tropical Bleyage"},{"title":"Got The Crystals","artist":"Imaginarium"},{"title":"Primary Effect","artist":"Manmachine"},{"title":"Spirale","artist":"Middle Mode"},{"title":"Circuit Data","artist":"Makida"},{"title":"Age of Revolution","artist":"Sideform"},{"title":"Daybreak","artist":"Arhetip"},{"title":"The Source","artist":"Nerso"},{"title":"The Great Escape","artist":"Subliminal Codes"},{"title":"Symbiosis - Arhetip Remix","artist":"Ectima, Arhetip"},{"title":"3 Quartos - Ectima Remix","artist":"Burn In Noise, Ectima"},{"title":"Rising Temple","artist":"Vertex, Lydia Delay"},{"title":"Lethal","artist":"Dark Soho"},{"title":"Fractality","artist":"Visua, Norma Project"},{"title":"Mycelium Morning","artist":"Xenoben"},{"title":"Shaman Daze","artist":"Xenoben"},{"title":"Deep State","artist":"Sonic Entity"},{"title":"Hemija - Shake Remix","artist":"Molok, Vertex, Subliminal Codes, Shake"},{"title":"From Darkness To Light","artist":"Shake"},{"title":"Messier 74","artist":"Zyce"},{"title":"Messier 83","artist":"Zyce"},{"title":"Reborn","artist":"Vertex"},{"title":"Sonic Form","artist":"Sonic Entity, Sideform"},{"title":"Shockwave","artist":"E-Clip"},{"title":"Dreamcatcher","artist":"Sonic Entity"},{"title":"Preda2r - Album Mix","artist":"Shake"},{"title":"Cosmic Web Cut 2","artist":"Lyktum"},{"title":"Black Essence - Nerso Remix","artist":"Aquafeel, Nerso"},{"title":"Son of Night - Shogan Remix","artist":"Zyce, Gaudium, Shogan"},{"title":"Real Lies","artist":"Waveform"},{"title":"Symbiosis - Arhetip Remix","artist":"Ectima, Arhetip"},{"title":"Become One With The Drum","artist":"Flegma"},{"title":"Road To Jangala (Album Intro)","artist":"Flegma"},{"title":"Bengal","artist":"Flegma, Zyce"},{"title":"Become One With The Drum","artist":"Flegma"},{"title":"Shalula","artist":"Flegma, Talpa"},{"title":"Echoes From Jangala","artist":"Flegma"},{"title":"Adrenaline - Flegma Remix","artist":"Liquid Soul, Flegma"},{"title":"Waiting For The Sun","artist":"Flegma"},{"title":"Soul Protector - Album Mix","artist":"Flegma"},{"title":"Sundarbans (Album Outro)","artist":"Flegma"},{"title":"Ayala","artist":"Zyce, Flegma, Deya Dova"},{"title":"Distorted Perception","artist":"Zyce"},{"title":"Shiva - Flegma Remix","artist":"Zyce, Morten Granau, Flegma"},{"title":"Telema","artist":"Talpa, Flegma"},{"title":"Tama - Tijah Remix","artist":"Flegma, Tijah"},{"title":"Chrysalis","artist":"Flegma"},{"title":"Bring On The Science","artist":"Talpa, Align"},{"title":"This is","artist":"Talpa"},{"title":"The End","artist":"Talpa"},{"title":"Malfunction","artist":"Talpa"},{"title":"We Come In Peace - Talpa Remix","artist":"Liquid Soul, Zyce, Solar Kid, Talpa"},{"title":"Platinum","artist":"Perception"},{"title":"Lions Gate","artist":"Vertex"},{"title":"Tripticon - Vertex Remix","artist":"Ticon, Vertex"},{"title":"Freedom","artist":"Praying-Mantis, Static Movement, Vertex"},{"title":"Angels Fire","artist":"Invisible Reality, Vertex"},{"title":"Beams Of Light","artist":"Vertex"},{"title":"Foothold","artist":"Ectima"},{"title":"Last Room","artist":"Ectima"},{"title":"First Dose Of DMT - Tech Mix","artist":"Ectima"},{"title":"PsyBizarre","artist":"Flegma"},{"title":"Natural Law","artist":"Xandar"},{"title":"Tree Of Life","artist":"Vertex"},{"title":"Realive","artist":"Perception"},{"title":"We Are Thoughts","artist":"Groundbass, Tijah, Perception"},{"title":"Biological","artist":"Paradox (IL)"},{"title":"Bauk","artist":"Ectima"},{"title":"Unblock Your Mind","artist":"Perception"},{"title":"Echoes","artist":"Oxiv"},{"title":"The Ritual - Cosmic Flow Remix","artist":"Zyce, Cosmic Flow"},{"title":"Star Dust - Aquafeel Remix","artist":"Zyce, Aquafeel"},{"title":"Other Perspectives","artist":"DX"},{"title":"Bela Vila","artist":"Xandar"},{"title":"Sun Bird","artist":"Zyce, Flegma"}]